<PAMDataset>
  <PAMRasterBand band="1">
    <Description>Band_1</Description>
    <Histograms>
      <HistItem>
        <HistMin>-2.652306079864502</HistMin>
        <HistMax>28.03700256347656</HistMax>
        <BucketCount>256</BucketCount>
        <IncludeOutOfRange>1</IncludeOutOfRange>
        <Approximate>0</Approximate>
        <HistCounts>14011|0|1|1|0|0|0|0|0|0|0|0|2|0|0|7|0|0|0|2|0|0|0|0|3|0|0|0|0|0|0|4|0|2|0|0|0|0|0|0|0|0|0|0|0|0|0|0|0|0|2|0|0|0|0|0|2|0|0|0|0|0|0|1|0|0|0|0|0|0|0|9|0|0|0|0|0|0|0|0|0|0|0|0|0|0|0|0|0|0|0|0|0|0|2|0|0|0|0|0|2|0|0|0|0|0|0|0|0|0|0|0|0|0|0|2|0|0|0|0|0|0|2|0|0|0|0|0|0|2|0|0|0|0|0|0|0|0|0|0|0|0|0|0|0|0|0|0|0|12|0|0|0|0|0|0|0|0|3|0|0|0|4|0|0|0|0|0|0|0|0|0|0|0|0|0|0|16|0|0|0|0|4|0|0|0|0|0|0|0|0|0|0|0|0|0|0|0|7|0|0|0|0|0|0|0|0|0|0|2|0|0|0|0|0|0|0|0|0|0|0|0|0|0|0|0|0|4|0|0|0|0|0|0|2|0|0|0|0|0|0|5|0|0|0|0|0|4|0|0|0|0|0|0|0|5</HistCounts>
      </HistItem>
    </Histograms>
    <Metadata>
      <MDI key="STATISTICS_MINIMUM">-2.6523060798645</MDI>
      <MDI key="STATISTICS_MAXIMUM">28.037002563477</MDI>
      <MDI key="STATISTICS_MEAN">-2.5191269645353</MDI>
      <MDI key="STATISTICS_STDDEV">1.6968689450886</MDI>
      <MDI key="STATISTICS_MEDIAN">-2.652306</MDI>
      <MDI key="STATISTICS_COUNT">14125.000000</MDI>
      <MDI key="STATISTICS_SKIPFACTORX">1</MDI>
      <MDI key="STATISTICS_SKIPFACTORY">1</MDI>
      <MDI key="STATISTICS_EXCLUDEDVALUES"></MDI>
      <MDI key="STATISTICS_COVARIANCES">2.879364216806041</MDI>
    </Metadata>
  </PAMRasterBand>
</PAMDataset>
